{
  "svelte.enable-ts-plugin": true,
  "javascript.suggest.autoImports": true,
  "typescript.suggest.autoImports": true,
  "rust-analyzer.enable": true,
  "rust-analyzer.server.path": "~/.rustup/toolchains/stable-aarch64-apple-darwin/bin/rust-analyzer",
  "rust-analyzer.cargo.features": "all",
  "rust-analyzer.checkOnSave.enable": true,
  "rust-analyzer.cargo.autoreload": true,
  "diagnostic.virtualText": true,
  "diagnostic.virtualTextCurrentLineOnly": false,
  "diagnostic.virtualTextPrefix": "▪ ",
  "diagnostic.errorSign": "",
  "diagnostic.warningSign": "⚠",
  "diagnostic.infoSign": "ⓘ",
  "diagnostic.hintSign": "\uf834",
  "diagnostic.virtualTextLimitInOneLine": 1
}
